{"sharing":{"linkSharingEnabled":false},"_id":"5f5537ee8b3e3b3d0d4bef1f","name":"Skeleton Collection (Copy)","description":"This is collection of common monsters turned skeleton.\n\nSkeletons are undead.\n\nSkeletons have a vulnerability to bludgeoning and a resistance to poison. They are immune to the exhausted and poisoned condition.\n\nSkeletons retain their strength and dexterity. Their constitution, intelligence, wisdom and charisma is uniform with other animated skeletons.\n\nArmor class is reduced by 2 and equipped armor is reduced to armor scraps.","ownerId":"5f5537378b3e3b3d0d4bef13","__v":0,"owner":{"_id":"5f5537378b3e3b3d0d4bef13","username":"jwinget"},"lastActive":"2020-09-06T19:26:39.126Z","creaturesLoading":false,"creatures":
    [{"flavor":{"faction":"","environment":"","description":"","nameIsProper":false,"imageUrl":"","descriptionHtml":""},"stats":{"size":"Medium","race":"Undead","alignment":"Unaligned","armorType":"","armorClass":10,"numHitDie":3,"speed":"30 ft., climb 30 ft.","abilityScores":{"strength":16,"dexterity":14,"constitution":15,"intelligence":6,"wisdom":8,"charisma":5},"proficiencyBonus":2,"damageVulnerabilities":["Bludgeoning"],"damageResistances":["Poison"],"damageImmunities":[],"conditionImmunities":["Exhaustion","Poisoned"],"senses":["passive Perception 13"],"languages":[],"challengeRating":0.5,"experiencePoints":100,"legendaryActionsPerRound":3,"legendaryActionsDescription":"","savingThrows":[],"skills":[{"name":"Athletics","proficient":true,"modifier":5,"modifierStr":"Athletics +5","$$hashKey":"object:50325"},{"name":"Perception","proficient":true,"modifier":1,"modifierStr":"Perception +1","$$hashKey":"object:50326"}],"additionalAbilities":[],"actions":[{"name":"Multiattack","description":"The ape makes two fist attacks.","descriptionHtml":{},"$$hashKey":"object:50290"},{"name":"Fist","description":"Melee Weapon Attack: +5 to hit, reach 5 ft., one target. Hit: 6 (1d6 + 3) bludgeoning damage.","descriptionHtml":{},"$$hashKey":"object:50291"},{"name":"Rock","description":"Ranged Weapon Attack: +5 to hit, range 25/50 ft., one target. Hit: 6 (1d6 + 3) bludgeoning damage.","descriptionHtml":{},"$$hashKey":"object:50292"}],"reactions":[],"legendaryActions":[],"hitDieSize":8,"abilityScoreModifiers":{"strength":3,"dexterity":2,"constitution":2,"intelligence":-2,"wisdom":-1,"charisma":-3},"abilityScoreStrs":{"strength":"16 (+3)","dexterity":"14 (+2)","constitution":"15 (+2)","intelligence":"6 (–2)","wisdom":"8 (–1)","charisma":"5 (–3)"},"extraHealthFromConstitution":6,"hitPoints":19,"hitPointsStr":"19 (3d8 + 6)","passivePerception":11,"challengeRatingStr":"1/2"},"sharing":{"linkSharingEnabled":false},"_id":"5f5537ee8b3e3b3d0d4bef20","name":"Ape Skeleton","__v":0,"bestiaryId":"5f5537ee8b3e3b3d0d4bef1f"},
        {"flavor":{"faction":"","environment":"","description":"","nameIsProper":false,"imageUrl":"","descriptionHtml":""},"stats":{"size":"Medium","race":"Undead","alignment":"Lawful Evil","armorType":"Natural Armor","armorClass":9,"numHitDie":3,"speed":"40 ft., climb 30 ft.","abilityScores":{"strength":15,"dexterity":10,"constitution":15,"intelligence":6,"wisdom":8,"charisma":5},"proficiencyBonus":2,"damageVulnerabilities":["Bludgeoning"],"damageResistances":["Poison"],"damageImmunities":[],"conditionImmunities":["Exhaustion","Poisoned"],"senses":[],"languages":[],"challengeRating":0.5,"experiencePoints":100,"legendaryActionsPerRound":3,"legendaryActionsDescription":"","savingThrows":[],"skills":[],"additionalAbilities":[{"name":"Keen Smell","description":"The black bear has advantage on Wisdom (perception) checks that rely on smell.","descriptionHtml":{},"$$hashKey":"object:50369"}],"actions":[{"name":"Multiattack","description":"The bear makes two attacks: one with its bite and one with its claws.","descriptionHtml":{},"$$hashKey":"object:50374"},{"name":"Bite","description":"Melee Weapon Attack: +3 to hit, reach 5 ft., one target. Hit: 5 (1d6 + 2) piercing damage.","descriptionHtml":{},"$$hashKey":"object:50375"},{"name":"Claws","description":"Melee Weapon Attack: +3 to hit, reach 5 ft., one target. Hit: 7 (2d4 + 2) slashing damage.","descriptionHtml":{},"$$hashKey":"object:50376"}],"reactions":[],"legendaryActions":[],"hitDieSize":8,"armorTypeStr":"(Natural Armor)","abilityScoreModifiers":{"strength":2,"dexterity":0,"constitution":2,"intelligence":-2,"wisdom":-1,"charisma":-3},"abilityScoreStrs":{"strength":"15 (+2)","dexterity":"10 (+0)","constitution":"15 (+2)","intelligence":"6 (–2)","wisdom":"8 (–1)","charisma":"5 (–3)"},"extraHealthFromConstitution":6,"hitPoints":19,"hitPointsStr":"19 (3d8 + 6)","passivePerception":9,"challengeRatingStr":"1/2"},"sharing":{"linkSharingEnabled":false},"_id":"5f5537ee8b3e3b3d0d4bef21","name":"Black Bear Skeleton","__v":0,"bestiaryId":"5f5537ee8b3e3b3d0d4bef1f"},
            {"flavor":{"faction":"","environment":"","description":"","nameIsProper":false,"imageUrl":"","descriptionHtml":""},"stats":{"size":"Small","race":"Undead","alignment":"Lawful Evil","armorType":"","armorClass":8,"numHitDie":2,"speed":"30 ft.","abilityScores":{"strength":10,"dexterity":10,"constitution":15,"intelligence":6,"wisdom":8,"charisma":5},"proficiencyBonus":2,"damageVulnerabilities":["Bludgeoning"],"damageResistances":["Poison"],"damageImmunities":[],"conditionImmunities":["Exhaustion","Poisoned"],"senses":["darkvision 60ft."],"languages":["Understands Common, Halfling but cannot speak"],"challengeRating":0,"experiencePoints":25,"legendaryActionsPerRound":3,"legendaryActionsDescription":"","savingThrows":[],"skills":[],"additionalAbilities":[],"actions":[{"name":"Club","description":"<i>Melee Weapon Attack:</i> +2 to hit, reach 5 ft., one creature. <i>Hit:</i> 2 (1d4) bludgeoning damage.","descriptionHtml":{},"$$hashKey":"object:50641"}],"reactions":[],"legendaryActions":[],"hitDieSize":6,"abilityScoreModifiers":{"strength":0,"dexterity":0,"constitution":2,"intelligence":-2,"wisdom":-1,"charisma":-3},"abilityScoreStrs":{"strength":"10 (+0)","dexterity":"10 (+0)","constitution":"15 (+2)","intelligence":"6 (–2)","wisdom":"8 (–1)","charisma":"5 (–3)"},"extraHealthFromConstitution":4,"hitPoints":11,"hitPointsStr":"11 (2d6 + 4)","passivePerception":9,"challengeRatingStr":"0"},"sharing":{"linkSharingEnabled":false},"_id":"5f5537ef8b3e3b3d0d4bef23","name":"Commoner Skeleton","__v":0,"bestiaryId":"5f5537ee8b3e3b3d0d4bef1f"},{"flavor":{"faction":"","environment":"","description":"","nameIsProper":false,"imageUrl":"","descriptionHtml":""},"stats":{"size":"Large","race":"Undead","alignment":"Lawful Evil","armorType":"Natural Armor","armorClass":9,"numHitDie":4,"speed":"40 ft., climb 30 ft.","abilityScores":{"strength":19,"dexterity":10,"constitution":15,"intelligence":6,"wisdom":8,"charisma":5},"proficiencyBonus":1,"damageVulnerabilities":["Bludgeoning"],"damageResistances":["Poison"],"damageImmunities":[],"conditionImmunities":["Exhaustion","Poisoned"],"senses":[],"languages":[],"challengeRating":1,"experiencePoints":200,"legendaryActionsPerRound":3,"legendaryActionsDescription":"","savingThrows":[],"skills":[{"name":"Perception","value":3,"proficient":false,"modifier":3,"modifierStr":"Perception +3","$$hashKey":"object:50486"}],"additionalAbilities":[{"name":"Keen Smell","description":"The brown bear skeleton has advantage on Wisdom (perception) checks that rely on smell.","descriptionHtml":{},"$$hashKey":"object:50446"}],"actions":[{"name":"Multiattack","description":"The bear makes two attacks: one with its bite and one with its claws.","descriptionHtml":{},"$$hashKey":"object:50451"},{"name":"Bite","description":"Weapon Attack: +5 to hit, reach 5 ft., one target. Hit: 8 (1d8 + 4) piercing damage.","descriptionHtml":{},"$$hashKey":"object:50452"},{"name":"Claws","description":"Melee Weapon Attack: +5 to hit, reach 5 ft., one target. Hit: 11 (2d6 + 4) slashing damage.","descriptionHtml":{},"$$hashKey":"object:50453"}],"reactions":[],"legendaryActions":[],"hitDieSize":10,"armorTypeStr":"(Natural Armor)","abilityScoreModifiers":{"strength":4,"dexterity":0,"constitution":2,"intelligence":-2,"wisdom":-1,"charisma":-3},"abilityScoreStrs":{"strength":"19 (+4)","dexterity":"10 (+0)","constitution":"15 (+2)","intelligence":"6 (–2)","wisdom":"8 (–1)","charisma":"5 (–3)"},"extraHealthFromConstitution":8,"hitPoints":30,"hitPointsStr":"30 (4d10 + 8)","passivePerception":13,"challengeRatingStr":"1"},"sharing":{"linkSharingEnabled":false},"_id":"5f5537ef8b3e3b3d0d4bef22","name":"Brown Bear Skeleton","__v":0,"bestiaryId":"5f5537ee8b3e3b3d0d4bef1f"},{"flavor":{"faction":"","environment":"","description":"","nameIsProper":false,"imageUrl":"","descriptionHtml":""},"stats":{"size":"Medium","race":"Undead (goblinoid)","alignment":"Lawful Evil","armorType":"Armor Scraps, Shield","armorClass":14,"numHitDie":5,"speed":"30 ft.","abilityScores":{"strength":15,"dexterity":14,"constitution":15,"intelligence":6,"wisdom":8,"charisma":5},"proficiencyBonus":2,"damageVulnerabilities":["Bludgeoning"],"damageResistances":["Poison"],"damageImmunities":[],"conditionImmunities":["Exhaustion","Poisoned"],"senses":["darkvision 60 ft."],"languages":["Understands","Common","Goblin","but cannot speak"],"challengeRating":1,"experiencePoints":200,"legendaryActionsPerRound":3,"legendaryActionsDescription":"","savingThrows":[],"skills":[{"name":"Stealth","value":6,"proficient":false,"modifier":6,"modifierStr":"Stealth +6","$$hashKey":"object:50574"},{"name":"Survival","value":2,"proficient":false,"modifier":2,"modifierStr":"Survival +2","$$hashKey":"object:50575"}],"additionalAbilities":[{"name":"Brute","description":"A melee weapon deals one extra die of its damage when the bugbear skeleton hits with it.","descriptionHtml":{},"$$hashKey":"object:50534"},{"name":"Suprise Attack","description":"If the bugbear skeleton surprises a creature and hits it with an attack during the first round of combat, the target takes an extra 7 (2d6) damage from the attack.","descriptionHtml":{},"$$hashKey":"object:50535"}],"actions":[{"name":"Morningstar","description":"Melee Weapon Attack: +4 to hit, reach 5 ft., one target. Hit: 11 (2d8 + 2) piercing damage.","descriptionHtml":{},"$$hashKey":"object:50542"},{"name":"Javelin","description":"Melee or Ranged Weapon Attack: +4 to hit, reach 5 ft. or range 30/120 ft., one target. Hit: 9 (2d6 + 2) piercing damage in melee or 5 (1d6 + 2) piercing damage at range.","descriptionHtml":{},"$$hashKey":"object:50543"}],"reactions":[],"legendaryActions":[],"hitDieSize":8,"armorTypeStr":"(Armor Scraps, Shield)","abilityScoreModifiers":{"strength":2,"dexterity":2,"constitution":2,"intelligence":-2,"wisdom":-1,"charisma":-3},"abilityScoreStrs":{"strength":"15 (+2)","dexterity":"14 (+2)","constitution":"15 (+2)","intelligence":"6 (–2)","wisdom":"8 (–1)","charisma":"5 (–3)"},"extraHealthFromConstitution":10,"hitPoints":32,"hitPointsStr":"32 (5d8 + 10)","passivePerception":9,"challengeRatingStr":"1"},"sharing":{"linkSharingEnabled":false},"_id":"5f5537ef8b3e3b3d0d4bef24","name":"Bugbear Skeleton","__v":0,"bestiaryId":"5f5537ee8b3e3b3d0d4bef1f"},{"flavor":{"faction":"","environment":"","description":"","nameIsProper":false,"imageUrl":"","descriptionHtml":""},"stats":{"size":"Small","race":"Undead","alignment":"Lawful Evil","armorType":"Armor Scraps, Shield","armorClass":15,"numHitDie":6,"speed":"30 ft.","abilityScores":{"strength":10,"dexterity":14,"constitution":15,"intelligence":6,"wisdom":8,"charisma":5},"proficiencyBonus":2,"damageVulnerabilities":["Bludgeoning"],"damageResistances":["Poison"],"damageImmunities":[],"conditionImmunities":["Exhaustion","Poisoned"],"senses":["darkvision 60ft."],"languages":["Understands Common, Goblin, but cannot speak"],"challengeRating":1,"experiencePoints":200,"legendaryActionsPerRound":3,"legendaryActionsDescription":"","savingThrows":[],"skills":[{"name":"Stealth","proficient":false,"value":6,"modifier":6,"modifierStr":"Stealth +6","$$hashKey":"object:50761"}],"additionalAbilities":[{"name":"Nimble Escape","description":"The skeleton goblin can take the Disengage or Hide action as a bonus action on each of its turns.","descriptionHtml":{},"$$hashKey":"object:50716"}],"actions":[{"name":"Multiattack","description":"The goblin makes two attacks with its scimitar. The second attack has disadvantage.","descriptionHtml":{},"$$hashKey":"object:50721"},{"name":"Scimitar","description":"<i>Melee Weapon Attack:</i> +4 to hit, reach 5 ft., one creature. <i>Hit:</i> 5 (1d6 + 2) slashing damage.","descriptionHtml":{},"$$hashKey":"object:50722"},{"name":"Shortbow","description":"<i>Ranged Weapon Attack:</i> +4 to hit, range 80/320 ft., one creature. <i>Hit:</i> 5 (1d6 + 2) piercing damage.","descriptionHtml":{},"$$hashKey":"object:50723"}],"reactions":[{"name":"Redirect Attack.","description":"When a creature the goblin can see targets it with an attack, the goblin chooses another goblin within 5 feet of it. The two goblins swap places, and the chosen goblin becomes the target instead.","descriptionHtml":{},"$$hashKey":"object:50732"}],"legendaryActions":[],"hitDieSize":6,"armorTypeStr":"(Armor Scraps, Shield)","abilityScoreModifiers":{"strength":0,"dexterity":2,"constitution":2,"intelligence":-2,"wisdom":-1,"charisma":-3},"abilityScoreStrs":{"strength":"10 (+0)","dexterity":"14 (+2)","constitution":"15 (+2)","intelligence":"6 (–2)","wisdom":"8 (–1)","charisma":"5 (–3)"},"extraHealthFromConstitution":12,"hitPoints":33,"hitPointsStr":"33 (6d6 + 12)","passivePerception":9,"challengeRatingStr":"1"},"sharing":{"linkSharingEnabled":false},"_id":"5f5537ef8b3e3b3d0d4bef25","name":"Goblin Boss Skeleton","__v":0,"bestiaryId":"5f5537ee8b3e3b3d0d4bef1f"},{"flavor":{"faction":"","environment":"","description":"","nameIsProper":false,"imageUrl":"","descriptionHtml":""},"stats":{"size":"Small","race":"Undead","alignment":"Lawful Evil","armorType":"Armor Scraps, Shield","armorClass":13,"numHitDie":2,"speed":"30 ft.","abilityScores":{"strength":8,"dexterity":14,"constitution":15,"intelligence":6,"wisdom":8,"charisma":5},"proficiencyBonus":2,"damageVulnerabilities":["Bludgeoning"],"damageResistances":["Poison"],"damageImmunities":[],"conditionImmunities":["Exhaustion","Poisoned"],"senses":["darkvision 60ft."],"languages":["Understands Common, Goblin, but cannot speak"],"challengeRating":0.25,"experiencePoints":50,"legendaryActionsPerRound":3,"legendaryActionsDescription":"","savingThrows":[],"skills":[],"additionalAbilities":[{"name":"Nimble Escape","description":"The skeleton goblin can take the Disengage or Hide action as a bonus action on each of its turns.","descriptionHtml":{},"$$hashKey":"object:50809"}],"actions":[{"name":"Scimitar","description":"<i>Melee Weapon Attack:</i> +4 to hit, reach 5 ft., one creature. <i>Hit:</i> 5 (1d6 + 2) slashing damage.","descriptionHtml":{},"$$hashKey":"object:50814"},{"name":"Shortbow","description":"<i>Ranged Weapon Attack:</i> +4 to hit, range 80/320 ft., one creature. <i>Hit:</i> 5 (1d6 + 2) piercing damage.","descriptionHtml":{},"$$hashKey":"object:50815"}],"reactions":[],"legendaryActions":[],"hitDieSize":6,"armorTypeStr":"(Armor Scraps, Shield)","abilityScoreModifiers":{"strength":-1,"dexterity":2,"constitution":2,"intelligence":-2,"wisdom":-1,"charisma":-3},"abilityScoreStrs":{"strength":"8 (–1)","dexterity":"14 (+2)","constitution":"15 (+2)","intelligence":"6 (–2)","wisdom":"8 (–1)","charisma":"5 (–3)"},"extraHealthFromConstitution":4,"hitPoints":11,"hitPointsStr":"11 (2d6 + 4)","passivePerception":9,"challengeRatingStr":"1/4"},"sharing":{"linkSharingEnabled":false},"_id":"5f5537ef8b3e3b3d0d4bef26","name":"Goblin Skeleton","__v":0,"bestiaryId":"5f5537ee8b3e3b3d0d4bef1f"},{"flavor":{"faction":"","environment":"","description":"","nameIsProper":false,"imageUrl":"","descriptionHtml":""},"stats":{"size":"Small","race":"Undead","alignment":"Lawful Evil","armorType":"Armor Scraps, Shield","armorClass":14,"numHitDie":2,"speed":"30 ft.","abilityScores":{"strength":13,"dexterity":12,"constitution":15,"intelligence":6,"wisdom":8,"charisma":5},"proficiencyBonus":2,"damageVulnerabilities":["Bludgeoning"],"damageResistances":["Poison"],"damageImmunities":[],"conditionImmunities":["Exhaustion","Poisoned"],"senses":[],"languages":["Understands Common, Halfling, but cannot speak"],"challengeRating":0.125,"experiencePoints":25,"legendaryActionsPerRound":3,"legendaryActionsDescription":"","savingThrows":[],"skills":[{"name":"Perception","value":2,"proficient":false,"modifier":2,"modifierStr":"Perception +2","$$hashKey":"object:50916"}],"additionalAbilities":[],"actions":[{"name":"Spear","description":"Melee or Ranged Weapon Attack: +3 to hit, reach 5 ft. or range 20/60 ft., one target. Hit: 4 (1d6 + 1) piercing damage or 5 (1d8 + 1) piercing damage if used with two hands to make a melee attack.","descriptionHtml":{},"$$hashKey":"object:50887"}],"reactions":[],"legendaryActions":[],"hitDieSize":6,"armorTypeStr":"(Armor Scraps, Shield)","abilityScoreModifiers":{"strength":1,"dexterity":1,"constitution":2,"intelligence":-2,"wisdom":-1,"charisma":-3},"abilityScoreStrs":{"strength":"13 (+1)","dexterity":"12 (+1)","constitution":"15 (+2)","intelligence":"6 (–2)","wisdom":"8 (–1)","charisma":"5 (–3)"},"extraHealthFromConstitution":4,"hitPoints":11,"hitPointsStr":"11 (2d6 + 4)","passivePerception":12,"challengeRatingStr":"1/8"},"sharing":{"linkSharingEnabled":false},"_id":"5f5537ef8b3e3b3d0d4bef27","name":"Guard Skeleton","__v":0,"bestiaryId":"5f5537ee8b3e3b3d0d4bef1f"},{"flavor":{"faction":"","environment":"","description":"","nameIsProper":false,"imageUrl":"","descriptionHtml":""},"stats":{"size":"Medium","race":"Undead (Goblinoid)","alignment":"Lawful Evil","armorType":"Armor Scraps, Shield","armorClass":16,"numHitDie":2,"speed":"30 ft.","abilityScores":{"strength":13,"dexterity":12,"constitution":15,"intelligence":6,"wisdom":8,"charisma":5},"proficiencyBonus":2,"damageVulnerabilities":["Bludgeoning"],"damageResistances":["Poison"],"damageImmunities":[],"conditionImmunities":["Exhaustion","Poisoned"],"senses":["darkvision 60 ft."],"languages":["Common","Goblin"],"challengeRating":0.5,"experiencePoints":100,"legendaryActionsPerRound":3,"legendaryActionsDescription":"","savingThrows":[],"skills":[],"additionalAbilities":[{"name":"Martial Advantage","description":"Once per turn, the hobgoblin skeleton can deal an extra 7 (2d6) damage to a creature it hits with a weapon attack if that creature is within 5 feet of an ally of the hobgoblin skeleton that isn’t incapacitated.","descriptionHtml":{},"$$hashKey":"object:50964"}],"actions":[{"name":"Longsword","description":"Melee Weapon Attack: +3 to hit, reach 5 ft., one target. Hit: 5 (1d8 + 1) slashing damage, or 6 (1d10 + 1) slashing damage if used with two hands.","descriptionHtml":{},"$$hashKey":"object:50969"},{"name":"Longbow","description":"Ranged Weapon Attack: +3 to hit, range 150/600 ft., one target. Hit: 5 (1d8 + 1) piercing damage.","descriptionHtml":{},"$$hashKey":"object:50970"}],"reactions":[],"legendaryActions":[],"hitDieSize":8,"armorTypeStr":"(Armor Scraps, Shield)","abilityScoreModifiers":{"strength":1,"dexterity":1,"constitution":2,"intelligence":-2,"wisdom":-1,"charisma":-3},"abilityScoreStrs":{"strength":"13 (+1)","dexterity":"12 (+1)","constitution":"15 (+2)","intelligence":"6 (–2)","wisdom":"8 (–1)","charisma":"5 (–3)"},"extraHealthFromConstitution":4,"hitPoints":13,"hitPointsStr":"13 (2d8 + 4)","passivePerception":9,"challengeRatingStr":"1/2"},"sharing":{"linkSharingEnabled":false},"_id":"5f5537ef8b3e3b3d0d4bef28","name":"Hobgoblin Skeleton","__v":0,"bestiaryId":"5f5537ee8b3e3b3d0d4bef1f"},{"flavor":{"faction":"","environment":"","description":"","nameIsProper":false,"imageUrl":"","descriptionHtml":""},"stats":{"size":"Small","race":"Undead (Kobold)","alignment":"Lawful Evil","armorType":"","armorClass":10,"numHitDie":2,"speed":"30 ft.","abilityScores":{"strength":7,"dexterity":15,"constitution":15,"intelligence":6,"wisdom":8,"charisma":5},"proficiencyBonus":2,"damageVulnerabilities":["Bludgeoning"],"damageResistances":["Poison"],"damageImmunities":[],"conditionImmunities":["Exhaustion","Poisoned"],"senses":["darkvision 60 ft."],"languages":["Understands","Common","Draconic","but cannot speak"],"challengeRating":0.125,"experiencePoints":25,"legendaryActionsPerRound":3,"legendaryActionsDescription":"","savingThrows":[],"skills":[],"additionalAbilities":[{"name":"Sunlight Sensitivity","description":"While in sunlight, the kobold skeleton has disadvantage on attack rolls, as well as on Wisdom (Perception) checks that rely on sight.","descriptionHtml":{},"$$hashKey":"object:51049"},{"name":"Pack Tactics","description":"The kobold skeleton has advantage on an attack roll against a creature if at least one of the kobold skeleton's allies is within 5 feet of the creature and the ally isn't incapacitated .","descriptionHtml":{},"$$hashKey":"object:51050"}],"actions":[{"name":"Dagger","description":"Melee Weapon Attack: +4 to hit, reach 5 ft., one target. Hit: 4 (1d4 + 2) piercing damage.","descriptionHtml":{},"$$hashKey":"object:51057"},{"name":"Sling","description":"Ranged Weapon Attack: +4 to hit, range 30/120 ft., one target. Hit: 4 (1d4 + 2) bludgeoning damage.","descriptionHtml":{},"$$hashKey":"object:51058"}],"reactions":[],"legendaryActions":[],"hitDieSize":6,"abilityScoreModifiers":{"strength":-2,"dexterity":2,"constitution":2,"intelligence":-2,"wisdom":-1,"charisma":-3},"abilityScoreStrs":{"strength":"7 (–2)","dexterity":"15 (+2)","constitution":"15 (+2)","intelligence":"6 (–2)","wisdom":"8 (–1)","charisma":"5 (–3)"},"extraHealthFromConstitution":4,"hitPoints":11,"hitPointsStr":"11 (2d6 + 4)","passivePerception":9,"challengeRatingStr":"1/8"},"sharing":{"linkSharingEnabled":false},"_id":"5f5537ef8b3e3b3d0d4bef29","name":"Kobold Skeleton","__v":0,"bestiaryId":"5f5537ee8b3e3b3d0d4bef1f"},{"flavor":{"faction":"","environment":"","description":"","nameIsProper":false,"imageUrl":"","descriptionHtml":""},"stats":{"size":"Large","race":"Undead","alignment":"Lawful Evil","armorType":"","armorClass":9,"numHitDie":7,"speed":"40 ft.","abilityScores":{"strength":19,"dexterity":8,"constitution":15,"intelligence":6,"wisdom":8,"charisma":5},"proficiencyBonus":2,"damageVulnerabilities":["Bludgeoning"],"damageResistances":["Poison"],"damageImmunities":[],"conditionImmunities":["Exhaustion","Poisoned"],"senses":["darkvision 60 ft."],"languages":["Common","Giant"],"challengeRating":2,"experiencePoints":450,"legendaryActionsPerRound":3,"legendaryActionsDescription":"","savingThrows":[],"skills":[],"additionalAbilities":[],"actions":[{"name":"Greatclub","description":"Melee Weapon Attack: +6 to hit, reach 5 ft., one target. Hit: 13 (2d8 + 4) bludgeoning damage.","descriptionHtml":{},"$$hashKey":"object:51147"},{"name":"Javelin","description":"Melee or Ranged Weapon Attack: +6 to hit, reach 5 ft. or range 30/120 ft., one target. Hit: 11 (2d6 + 4) piercing damage.","descriptionHtml":{},"$$hashKey":"object:51148"}],"reactions":[],"legendaryActions":[],"hitDieSize":10,"abilityScoreModifiers":{"strength":4,"dexterity":-1,"constitution":2,"intelligence":-2,"wisdom":-1,"charisma":-3},"abilityScoreStrs":{"strength":"19 (+4)","dexterity":"8 (–1)","constitution":"15 (+2)","intelligence":"6 (–2)","wisdom":"8 (–1)","charisma":"5 (–3)"},"extraHealthFromConstitution":14,"hitPoints":52,"hitPointsStr":"52 (7d10 + 14)","passivePerception":9,"challengeRatingStr":"2"},"sharing":{"linkSharingEnabled":false},"_id":"5f5537ef8b3e3b3d0d4bef2a","name":"Ogre Skeleton","__v":0,"bestiaryId":"5f5537ee8b3e3b3d0d4bef1f"},{"flavor":{"faction":"","environment":"","description":"","nameIsProper":false,"imageUrl":"","descriptionHtml":""},"stats":{"size":"Medium","race":"Undead (orc)","alignment":"Lawful Evil","armorType":"Armor Scraps","armorClass":11,"numHitDie":2,"speed":"30 ft.","abilityScores":{"strength":16,"dexterity":12,"constitution":15,"intelligence":6,"wisdom":8,"charisma":5},"proficiencyBonus":2,"damageVulnerabilities":["Bludgeoning"],"damageResistances":["Poison"],"damageImmunities":[],"conditionImmunities":["Exhaustion","Poisoned"],"senses":["darkvision 60 ft."],"languages":["Understands","Common","Orc","but cannot speak"],"challengeRating":0.5,"experiencePoints":100,"legendaryActionsPerRound":3,"legendaryActionsDescription":"","savingThrows":[],"skills":[{"name":"Intimidation","value":2,"proficient":false,"modifier":2,"modifierStr":"Intimidation +2","$$hashKey":"object:51266"}],"additionalAbilities":[{"name":"Aggressive","description":"As a bonus action, the orc can move up to its speed toward a hostile creature that it can see.","descriptionHtml":{},"$$hashKey":"object:51229"}],"actions":[{"name":"Greataxe","description":"Melee Weapon Attack: +5 to hit, reach 5 ft., one target. Hit: 9 (1d12 + 3) slashing damage.","descriptionHtml":{},"$$hashKey":"object:51234"},{"name":"Javelin","description":"Melee or Ranged Weapon Attack: +5 to hit, reach 5 ft. or range 30/120 ft., one target. Hit: 6 (1d6 + 3) piercing damage.","descriptionHtml":{},"$$hashKey":"object:51235"}],"reactions":[],"legendaryActions":[],"hitDieSize":8,"armorTypeStr":"(Armor Scraps)","abilityScoreModifiers":{"strength":3,"dexterity":1,"constitution":2,"intelligence":-2,"wisdom":-1,"charisma":-3},"abilityScoreStrs":{"strength":"16 (+3)","dexterity":"12 (+1)","constitution":"15 (+2)","intelligence":"6 (–2)","wisdom":"8 (–1)","charisma":"5 (–3)"},"extraHealthFromConstitution":4,"hitPoints":13,"hitPointsStr":"13 (2d8 + 4)","passivePerception":9,"challengeRatingStr":"1/2"},"sharing":{"linkSharingEnabled":false},"_id":"5f5537ef8b3e3b3d0d4bef2b","name":"Orc Skeleton","__v":0,"bestiaryId":"5f5537ee8b3e3b3d0d4bef1f"},{"flavor":{"faction":"","environment":"","description":"","nameIsProper":false,"imageUrl":"","descriptionHtml":""},"stats":{"size":"Large","race":"Undead","alignment":"Lawful Evil","armorType":"Natural Armor","armorClass":11,"numHitDie":7,"speed":"40 ft.","abilityScores":{"strength":20,"dexterity":12,"constitution":15,"intelligence":6,"wisdom":8,"charisma":5},"proficiencyBonus":2,"damageVulnerabilities":["Bludgeoning"],"damageResistances":["Poison"],"damageImmunities":[],"conditionImmunities":["Exhaustion","Poisoned"],"senses":["darkvision 60 ft."],"languages":[],"challengeRating":3,"experiencePoints":700,"legendaryActionsPerRound":3,"legendaryActionsDescription":"","savingThrows":[],"skills":[{"name":"Perception","value":3,"proficient":false,"modifier":3,"modifierStr":"Perception +3","$$hashKey":"object:51368"}],"additionalAbilities":[{"name":"Keen Sight and Smell","description":"The owlbear skeleton has advantage on Wisdom (Perception) checks that rely on sight or smell.","descriptionHtml":{},"$$hashKey":"object:51328"}],"actions":[{"name":"Multiattack","description":"The owlbear makes two attacks: one with its beak and one with its claws.","descriptionHtml":{},"$$hashKey":"object:51333"},{"name":"Beak","description":"Melee Weapon Attack: +7 to hit, reach 5 ft., one creature. Hit: 10 (1d10 + 5) piercing damage.","descriptionHtml":{},"$$hashKey":"object:51334"},{"name":"Claws","description":"Melee Weapon Attack: +7 to hit, reach 5 ft., one target. Hit: 14 (2d8 + 5) slashing damage.","descriptionHtml":{},"$$hashKey":"object:51335"}],"reactions":[],"legendaryActions":[],"hitDieSize":10,"armorTypeStr":"(Natural Armor)","abilityScoreModifiers":{"strength":5,"dexterity":1,"constitution":2,"intelligence":-2,"wisdom":-1,"charisma":-3},"abilityScoreStrs":{"strength":"20 (+5)","dexterity":"12 (+1)","constitution":"15 (+2)","intelligence":"6 (–2)","wisdom":"8 (–1)","charisma":"5 (–3)"},"extraHealthFromConstitution":14,"hitPoints":52,"hitPointsStr":"52 (7d10 + 14)","passivePerception":13,"challengeRatingStr":"3"},"sharing":{"linkSharingEnabled":false},"_id":"5f5537ef8b3e3b3d0d4bef2c","name":"Owlbear Skeleton","__v":0,"bestiaryId":"5f5537ee8b3e3b3d0d4bef1f"},{"flavor":{"faction":"","environment":"","description":"","nameIsProper":false,"imageUrl":"","descriptionHtml":""},"stats":{"size":"Medium","race":"undead","alignment":"lawful evil","armorType":"","armorClass":13,"numHitDie":2,"speed":"30 ft.","abilityScores":{"strength":10,"dexterity":14,"constitution":15,"intelligence":6,"wisdom":8,"charisma":5},"proficiencyBonus":0,"damageVulnerabilities":["bludgeoning"],"damageResistances":[],"damageImmunities":[],"conditionImmunities":["poisoned"],"senses":["darkvision 60 ft."],"languages":["understands all languages it spoke in life but can't speak"],"challengeRating":0.25,"experiencePoints":50,"legendaryActionsPerRound":3,"legendaryActionsDescription":"","savingThrows":[],"skills":[],"additionalAbilities":[],"actions":[{"name":"Shortsword","description":"Melee Weapon Attack: +4 to hit, reach 5 ft., one target. Hit: 5 (1d6 + 2) piercing damage.","descriptionHtml":{},"$$hashKey":"object:51414"},{"name":"Shortbow","description":"Ranged Weapon Attack: +4 to hit, range 80/320 ft., one target. Hit: 5 (1d6 + 2) piercing damage.","descriptionHtml":{},"$$hashKey":"object:51415"}],"reactions":[],"legendaryActions":[],"hitDieSize":8,"abilityScoreModifiers":{"strength":0,"dexterity":2,"constitution":2,"intelligence":-2,"wisdom":-1,"charisma":-3},"abilityScoreStrs":{"strength":"10 (+0)","dexterity":"14 (+2)","constitution":"15 (+2)","intelligence":"6 (–2)","wisdom":"8 (–1)","charisma":"5 (–3)"},"extraHealthFromConstitution":4,"hitPoints":13,"hitPointsStr":"13 (2d8 + 4)","passivePerception":9,"challengeRatingStr":"1/4"},"sharing":{"linkSharingEnabled":false},"_id":"5f5537ef8b3e3b3d0d4bef2d","name":"Skeleton","__v":0,"bestiaryId":"5f5537ee8b3e3b3d0d4bef1f"}]}